sonoffdiy/__init__.py
sonoffdiy/__version__.py
sonoffdiy/const.py
sonoffdiy/exceptions.py
sonoffdiy/models.py
sonoffdiy/sonoffdiy.py
sonoffdiy-0.1.0.dist-info/LICENSE.md
sonoffdiy-0.1.0.dist-info/METADATA
sonoffdiy-0.1.0.dist-info/WHEEL
sonoffdiy-0.1.0.dist-info/top_level.txt
sonoffdiy-0.1.0.dist-info/RECORD
