Metadata-Version: 2.1
Name: sonoffdiy
Version: 0.1.0
Summary: Asynchronous Python client for Sonoff DIY devices.
Home-page: https://github.com/frenck/python-sonoffdiy
Author: Franck Nijhof
Author-email: opensource@frenck.dev
License: MIT license
Keywords: sonoff,diy,api,async,client
Platform: UNKNOWN
Classifier: Development Status :: 4 - Beta
Classifier: Framework :: AsyncIO
Classifier: Intended Audience :: Developers
Classifier: License :: OSI Approved :: MIT License
Classifier: Natural Language :: English
Classifier: Programming Language :: Python :: 3.6
Classifier: Programming Language :: Python :: 3.7
Classifier: Programming Language :: Python :: 3.8
Classifier: Programming Language :: Python :: 3
Classifier: Topic :: Software Development :: Libraries :: Python Modules
Requires-Dist: aiohttp (>=3.0.0)
Requires-Dist: attrs (>=19.0.0)
Requires-Dist: yarl
